filesystem/__init__.py
filesystem/databasic.py
filesystem/dataerror.py
filesystem/datafile.py
filesystem/datafolder.py
py_filesystem-0.1.1.dist-info/METADATA
py_filesystem-0.1.1.dist-info/WHEEL
py_filesystem-0.1.1.dist-info/top_level.txt
py_filesystem-0.1.1.dist-info/RECORD
