Metadata-Version: 2.1
Name: py-filesystem
Version: 0.1.1
Summary: file and folder system information
Home-page: https://github.com/FredTourn/py-filesystem/
Author: FredTourn
Author-email: mz.bouba@free.fr
License: GPL
Keywords: file folder system
Platform: UNKNOWN
Classifier: Intended Audience :: Developers
Classifier: License :: OSI Approved :: BSD License
Classifier: Programming Language :: Python
Classifier: Programming Language :: Python :: 2.7
Classifier: Programming Language :: Python :: 3
Classifier: Programming Language :: Python :: 3.5
Classifier: Programming Language :: Python :: 3.6
Classifier: Programming Language :: Python :: 3.7
Classifier: Programming Language :: Python :: 3.8
Classifier: Programming Language :: Python :: 3.9
Requires-Python: >=2.7, !=3.0.*, !=3.1.*, !=3.2.*, !=3.3.*, !=3.4.*
Requires-Dist: python-magic (>=0.4.27)
